[
  {
    "id": "world_config_9",
    "round": "round_1",
    "customers": 15,
    "average amount": 1,
    "tennisBall": 1,
    "carrot": 1,
    "nenufar": 0,
    "nest": 0,
    "candle": 0,
    "pillow": 0,
    "blackLotus": 0,
    "bottle": 0,
    "coffee": 0,
    "sandwitch": 0,
    "croissant": 0
  },
  {
    "id": "world_config_9",
    "round": "round_2",
    "customers": 15,
    "average amount": 1,
    "tennisBall": 0,
    "carrot": 1,
    "nenufar": 2,
    "nest": 0,
    "candle": 0,
    "pillow": 0,
    "blackLotus": 0,
    "bottle": 1,
    "coffee": 0,
    "sandwitch": 0,
    "croissant": 0
  },
  {
    "id": "world_config_9",
    "round": "round_3",
    "customers": 10,
    "average amount": 2,
    "tennisBall": 0,
    "carrot": 1,
    "nenufar": 1,
    "nest": 0,
    "candle": 0,
    "pillow": 0,
    "blackLotus": 0,
    "bottle": 1,
    "coffee": 0,
    "sandwitch": 0,
    "croissant": 0
  },
  {
    "id": "world_config_9",
    "round": "round_4",
    "customers": 10,
    "average amount": 2,
    "tennisBall": 0,
    "carrot": 0,
    "nenufar": 1,
    "nest": 0,
    "candle": 0,
    "pillow": 0,
    "blackLotus": 0,
    "bottle": 1,
    "coffee": 0,
    "sandwitch": 0,
    "croissant": 0
  },
  {
    "id": "world_config_9",
    "round": "round_5",
    "customers": 10,
    "average amount": 1,
    "tennisBall": 0,
    "carrot": 0,
    "nenufar": 0,
    "nest": 1,
    "candle": 0,
    "pillow": 0,
    "blackLotus": 0,
    "bottle": 0,
    "coffee": 0,
    "sandwitch": 0,
    "croissant": 0
  },
  {
    "id": "world_config_9",
    "round": "round_6",
    "customers": 10,
    "average amount": 1,
    "tennisBall": 0,
    "carrot": 1,
    "nenufar": 0,
    "nest": 1,
    "candle": 0,
    "pillow": 0,
    "blackLotus": 0,
    "bottle": 0,
    "coffee": 0,
    "sandwitch": 0,
    "croissant": 0
  },
  {
    "id": "world_config_9",
    "round": "round_7",
    "customers": 10,
    "average amount": 1,
    "tennisBall": 1,
    "carrot": 0,
    "nenufar": 1,
    "nest": 1,
    "candle": 0,
    "pillow": 0,
    "blackLotus": 0,
    "bottle": 0,
    "coffee": 0,
    "sandwitch": 0,
    "croissant": 0
  },
  {
    "id": "world_config_9",
    "round": "round_8",
    "customers": 10,
    "average amount": 1,
    "tennisBall": 0,
    "carrot": 1,
    "nenufar": 0,
    "nest": 1,
    "candle": 0,
    "pillow": 0,
    "blackLotus": 0,
    "bottle": 1,
    "coffee": 0,
    "sandwitch": 0,
    "croissant": 0
  },
  {
    "id": "world_config_9",
    "round": "round_9",
    "customers": 20,
    "average amount": 2,
    "tennisBall": 0,
    "carrot": 0,
    "nenufar": 0,
    "nest": 1,
    "candle": 0,
    "pillow": 0,
    "blackLotus": 0,
    "bottle": 0,
    "coffee": 0,
    "sandwitch": 0,
    "croissant": 0
  }
]